{
	"info": {
		"_postman_id": "2c143887-492b-47d3-afaf-0913c9e91e71",
		"name": "S51-Requests",
		"schema": "https://schema.getpostman.com/json/collection/v2.1.0/collection.json",
		"_exporter_id": "27719350"
	},
	"item": [
		{
			"name": "getProduct route",
			"request": {
				"method": "GET",
				"header": [],
				"url": {
					"raw": "http://localhost:4000/products/64adf839e1ac01d5719002f3",
					"protocol": "http",
					"host": [
						"localhost"
					],
					"port": "4000",
					"path": [
						"products",
						"64adf839e1ac01d5719002f3"
					]
				}
			},
			"response": []
		},
		{
			"name": "archiveProduct route",
			"request": {
				"auth": {
					"type": "bearer",
					"bearer": [
						{
							"key": "token",
							"value": "eyJhbGciOiJIUzI1NiIsInR5cCI6IkpXVCJ9.eyJpZCI6IjY0YWQ3MjY2Mzc0MWIxNzIyNmYzYzI4MyIsImVtYWlsIjoieWFlQG1haWwuY29tIiwiaXNBZG1pbiI6dHJ1ZSwiaWF0IjoxNjg5MTIzMDYzfQ.rvY-nX7RPtXgo3LQVl5nWsM2pSSj7MnzM4c3ubHzuYQ",
							"type": "string"
						}
					]
				},
				"method": "PUT",
				"header": [],
				"url": {
					"raw": "http://localhost:4000/products/64ad7473b95a5789c6e385ba/archiveProduct",
					"protocol": "http",
					"host": [
						"localhost"
					],
					"port": "4000",
					"path": [
						"products",
						"64ad7473b95a5789c6e385ba",
						"archiveProduct"
					]
				}
			},
			"response": []
		},
		{
			"name": "activateProduct route",
			"request": {
				"auth": {
					"type": "bearer",
					"bearer": [
						{
							"key": "token",
							"value": "eyJhbGciOiJIUzI1NiIsInR5cCI6IkpXVCJ9.eyJpZCI6IjY0YWQ3MjY2Mzc0MWIxNzIyNmYzYzI4MyIsImVtYWlsIjoieWFlQG1haWwuY29tIiwiaXNBZG1pbiI6dHJ1ZSwiaWF0IjoxNjg5MTIzMDYzfQ.rvY-nX7RPtXgo3LQVl5nWsM2pSSj7MnzM4c3ubHzuYQ",
							"type": "string"
						}
					]
				},
				"method": "PUT",
				"header": [],
				"url": {
					"raw": "http://localhost:4000/products/64ad7473b95a5789c6e385ba/activateProduct",
					"protocol": "http",
					"host": [
						"localhost"
					],
					"port": "4000",
					"path": [
						"products",
						"64ad7473b95a5789c6e385ba",
						"activateProduct"
					]
				}
			},
			"response": []
		},
		{
			"name": "updateProduct route",
			"request": {
				"auth": {
					"type": "bearer",
					"bearer": [
						{
							"key": "token",
							"value": "eyJhbGciOiJIUzI1NiIsInR5cCI6IkpXVCJ9.eyJpZCI6IjY0YWQ3MjY2Mzc0MWIxNzIyNmYzYzI4MyIsImVtYWlsIjoieWFlQG1haWwuY29tIiwiaXNBZG1pbiI6dHJ1ZSwiaWF0IjoxNjg5MTIzMDYzfQ.rvY-nX7RPtXgo3LQVl5nWsM2pSSj7MnzM4c3ubHzuYQ",
							"type": "string"
						}
					]
				},
				"method": "PUT",
				"header": [],
				"body": {
					"mode": "raw",
					"raw": "{\r\n    \"name\": \"Song of Broken Pines\",\r\n    \"description\": \"A greatsword as light as the sigh of grass in the breeze, yet as merciless to the corrupt as a typhoon.\",\r\n    \"price\": \"40000\"\r\n}",
					"options": {
						"raw": {
							"language": "json"
						}
					}
				},
				"url": {
					"raw": "http://localhost:4000/products/64ad74efb95a5789c6e385bc/updateProduct",
					"protocol": "http",
					"host": [
						"localhost"
					],
					"port": "4000",
					"path": [
						"products",
						"64ad74efb95a5789c6e385bc",
						"updateProduct"
					]
				}
			},
			"response": []
		}
	]
}